kitbash/__init__.py
kitbash/gui/__init__.py
kitbash/gui/main_window.py
kitbash/gui/main_window.ui
kitbash/res/empty.sfz
kitbash/res/group_expanded.svg
kitbash/res/group_hidden.svg
kitbash/res/kitbash-icon.png
kitbash/scripts/bash_project.py
kitbash/styles/light.css
kitbash/styles/system.css
kitbash-1.2.2.dist-info/entry_points.txt
kitbash-1.2.2.dist-info/LICENSE
kitbash-1.2.2.dist-info/WHEEL
kitbash-1.2.2.dist-info/METADATA
kitbash-1.2.2.dist-info/RECORD
