Metadata-Version: 2.1
Name: kitbash
Version: 1.2.2
Summary: kitbash is a program you can use to combine parts of various SFZ files into a
Author-email: Leon Dionne <ldionne@dridesign.sh.cn>
Classifier: License :: OSI Approved :: GNU General Public License v3 or later (GPLv3+)
Requires-Dist: PyQt5
Requires-Dist: conn_jack >= 1.2.0
Requires-Dist: liquiphy
Requires-Dist: soundfile
Requires-Dist: sfzen >= 1.5.0
Requires-Dist: midi_notes >= 1.1.0
Requires-Dist: recent_items_list >= 1.1.1
Requires-Dist: soso_qt_extras >= 1.2.0
Project-URL: Home, https://github.com/Zen-Master-SoSo/kitbash
